accelbyte_py_sdk/api/qosm/__init__.py
accelbyte_py_sdk/api/qosm/errors.py
accelbyte_py_sdk/api/qosm/models/__init__.py
accelbyte_py_sdk/api/qosm/models/models_heartbeat_request.py
accelbyte_py_sdk/api/qosm/models/models_list_server_response.py
accelbyte_py_sdk/api/qosm/models/models_server.py
accelbyte_py_sdk/api/qosm/models/models_set_alias_request.py
accelbyte_py_sdk/api/qosm/models/models_update_server_request.py
accelbyte_py_sdk/api/qosm/models/response_error.py
accelbyte_py_sdk/api/qosm/operations/__init__.py
accelbyte_py_sdk/api/qosm/operations/admin/__init__.py
accelbyte_py_sdk/api/qosm/operations/admin/delete_server.py
accelbyte_py_sdk/api/qosm/operations/admin/set_server_alias.py
accelbyte_py_sdk/api/qosm/operations/admin/update_server_config.py
accelbyte_py_sdk/api/qosm/operations/public/__init__.py
accelbyte_py_sdk/api/qosm/operations/public/list_server.py
accelbyte_py_sdk/api/qosm/operations/public/list_server_per_namespace.py
accelbyte_py_sdk/api/qosm/operations/server/__init__.py
accelbyte_py_sdk/api/qosm/operations/server/heartbeat.py
accelbyte_py_sdk/api/qosm/wrappers/__init__.py
accelbyte_py_sdk/api/qosm/wrappers/_admin.py
accelbyte_py_sdk/api/qosm/wrappers/_public.py
accelbyte_py_sdk/api/qosm/wrappers/_server.py
accelbyte_py_sdk_service_qosm-0.14.0.dist-info/METADATA
accelbyte_py_sdk_service_qosm-0.14.0.dist-info/WHEEL
accelbyte_py_sdk_service_qosm-0.14.0.dist-info/top_level.txt
accelbyte_py_sdk_service_qosm-0.14.0.dist-info/RECORD
